pybibtex/__init__.py
pybibtex/pybibtex.py
pybibtex-0.3.0.dist-info/LICENSE
pybibtex-0.3.0.dist-info/METADATA
pybibtex-0.3.0.dist-info/WHEEL
pybibtex-0.3.0.dist-info/top_level.txt
pybibtex-0.3.0.dist-info/zip-safe
pybibtex-0.3.0.dist-info/RECORD
