Metadata-Version: 2.1
Name: pybibtex
Version: 0.3.0
Summary: Utility functions for creating citation references
Home-page: https://github.com/rasbt/pybibtex
Author: Sebastian Raschka
Author-email: mail@sebastianraschka.com
License: MIT
Keywords: bibtex
Platform: any
Classifier: License :: OSI Approved :: MIT License
Classifier: Development Status :: 5 - Production/Stable
Classifier: Operating System :: Microsoft :: Windows
Classifier: Operating System :: POSIX
Classifier: Operating System :: Unix
Classifier: Operating System :: MacOS
Classifier: Programming Language :: Python :: 3.6
